optimutils/__init__.py
optimutils/utils.py
optimutils-1.1.dist-info/LICENSE
optimutils-1.1.dist-info/METADATA
optimutils-1.1.dist-info/WHEEL
optimutils-1.1.dist-info/top_level.txt
optimutils-1.1.dist-info/RECORD
