Metadata-Version: 2.1
Name: optimutils
Version: 1.1
Summary: Tools for mathematical optimisation.
Author-email: Stefan Pfenninger <stefan@pfenninger.org>
Maintainer-email: Stefan Pfenninger <stefan@pfenninger.org>
License: MIT
Project-URL: repository, https://github.com/sjpfenninger/optimutils
Project-URL: changelog, https://github.com/sjpfenninger/optimutils/CHANGELOG.md
Classifier: Intended Audience :: Science/Research
Classifier: License :: OSI Approved :: Apache Software License
Classifier: Programming Language :: Python
Classifier: Programming Language :: Python :: 3
Classifier: Programming Language :: Python :: 3 :: Only
Requires-Python: >=3.10
License-File: LICENSE
Requires-Dist: pandas
Requires-Dist: pyomo <7,>=6
Requires-Dist: ipython
